DatasetHandler_Group_2/DatasetHandler_Group_2.py
DatasetHandler_Group_2/__init__.py
DatasetHandler_Group_2-0.2.0.dist-info/LICENSE.txt
DatasetHandler_Group_2-0.2.0.dist-info/METADATA
DatasetHandler_Group_2-0.2.0.dist-info/WHEEL
DatasetHandler_Group_2-0.2.0.dist-info/top_level.txt
DatasetHandler_Group_2-0.2.0.dist-info/RECORD
