Metadata-Version: 2.1
Name: DatasetHandler-Group-2
Version: 0.2.0
Summary: Dataset handler of group 2
Home-page: https://github.com/Group_2_DataHandler/Group_2_DataHandler
Author: Irati Azpilgain, Mikel Ballesteros, Ander Crespo, Estibaliz Cruz, Lucas Lafuente y Mikel Puerta
Author-email: mikel.puerta@alumni.mondragon.edu
Classifier: Programming Language :: Python :: 3
Classifier: License :: OSI Approved :: MIT License
Classifier: Operating System :: OS Independent
Requires-Python: >=3.6
License-File: LICENSE.txt
Requires-Dist: pandas
Requires-Dist: numpy
Requires-Dist: seaborn
Requires-Dist: matplotlib
Requires-Dist: scikit-learn
Requires-Dist: openpyxl
Requires-Dist: xlrd
